<?xml version="1.0" encoding="UTF-8"?>

<config xmlns:xsi="http://www.w3.org/2001/XMLSchema-instance" xsi:noNamespaceSchemaLocation="urn:magento:framework:ObjectManager/etc/config.xsd">
    <blocks>
        <block>
            <item name="file">home-categories-choice.html</item>
            <item name="title">Amasty JetTheme Homepage categories Block</item>
            <item name="identifier">amjet-homepage-categories</item>
            <item name="is_active">0</item>
        </block>

        <block>
            <item name="file">main-banner.html</item>
            <item name="title">Amasty JetTheme Homepage main banner Block</item>
            <item name="identifier">amjet-main-banner</item>
            <item name="is_active">0</item>
        </block>

        <block>
            <item name="file">secondary-banner.html</item>
            <item name="title">Amasty JetTheme Secondary Banner - Static</item>
            <item name="identifier">amjet-secondary-banner-static</item>
            <item name="is_active">0</item>
        </block>

        <block>
            <item name="file">secondary-banner-carousel.html</item>
            <item name="title">Amasty JetTheme Secondary Banner with Slider</item>
            <item name="identifier">amjet-secondary-banner-carousel</item>
            <item name="is_active">0</item>
        </block>

        <block>
            <item name="file">home-products.html</item>
            <item name="title">Amasty JetTheme Products from Category</item>
            <item name="identifier">amjet-products-homepage</item>
            <item name="is_active">0</item>
        </block>

        <block>
            <item name="file">homepage-block.html</item>
            <item name="title">Amasty JetTheme Homepage block</item>
            <item name="identifier">amjet-homepage-block</item>
            <item name="is_active">0</item>
        </block>

        <block>
            <item name="file">explore-more.html</item>
            <item name="title">Amasty JetTheme Explore More</item>
            <item name="identifier">amjet-explore-more</item>
            <item name="is_active">0</item>
        </block>

        <block>
            <item name="file">left-menu.html</item>
            <item name="title">Amasty JetTheme Left Menu</item>
            <item name="identifier">amjet-left-menu</item>
            <item name="is_active">0</item>
        </block>

        <block>
            <item name="file">products-preview.html</item>
            <item name="title">Amasty JetTheme Products Preview</item>
            <item name="identifier">amjet-products-preview</item>
            <item name="is_active">0</item>
        </block>
    </blocks>
</config>
